hyperscale/ozone/__init__.py
hyperscale/ozone/cfn_nag.py
hyperscale/ozone/cli.py
hyperscale/ozone/cloudtrail.py
hyperscale/ozone/iam.py
hyperscale/ozone/pipelines.py
hyperscale/ozone/route53resolver.py
hyperscale/ozone/rvm.py
hyperscale/ozone/rvm_lambda.py
hyperscale/ozone/s3.py
hyperscale_ozone-0.20.2.dist-info/METADATA
hyperscale_ozone-0.20.2.dist-info/WHEEL
hyperscale_ozone-0.20.2.dist-info/entry_points.txt
hyperscale_ozone-0.20.2.dist-info/licenses/LICENSE
hyperscale_ozone-0.20.2.dist-info/RECORD
