Metadata-Version: 2.4
Name: hyperscale-ozone
Version: 0.20.2
Summary: Higher-level constructs build on troposphere
Project-URL: repository, https://github.com/hyperscale-consulting/ozone
Author-email: Andy Caine <andy@hyperscale.consulting>, Henry Addico <henry@hyperscale.consulting>
License-Expression: MIT
License-File: LICENSE
Requires-Python: >=3.10
Requires-Dist: click>=8.2.1
Requires-Dist: troposphere>=4.9.4
